[
  { "id": 1, "name": "Vehuiah", "hebrew": "והויה" },
  { "id": 2, "name": "Jeliel", "hebrew": "יליאל" },
  { "id": 3, "name": "Sitael", "hebrew": "סיטאל" },
  { "id": 4, "name": "Elemiah", "hebrew": "עלמיה" },
  { "id": 5, "name": "Mahasiah", "hebrew": "מהשיה" },
  { "id": 6, "name": "Lelahel", "hebrew": "ללהאל" },
  { "id": 7, "name": "Achaiah", "hebrew": "אכאיה" },
  { "id": 8, "name": "Cahethel", "hebrew": "כהתאל" },
  { "id": 9, "name": "Haziel", "hebrew": "הזיאל" },
  { "id": 10, "name": "Aladiah", "hebrew": "אלדיה" },
  { "id": 11, "name": "Lauviah", "hebrew": "לאויה" },
  { "id": 12, "name": "Hahaiah", "hebrew": "ההעיה" },
  { "id": 13, "name": "Iezalel", "hebrew": "יזלאל" },
  { "id": 14, "name": "Mebahel", "hebrew": "מבהאל" },
  { "id": 15, "name": "Hariel", "hebrew": "הריאל" },
  { "id": 16, "name": "Hakamiah", "hebrew": "הקמיה" },
  { "id": 17, "name": "Lauviah", "hebrew": "לאויה" },
  { "id": 18, "name": "Caliel", "hebrew": "כליאל" },
  { "id": 19, "name": "Leuviah", "hebrew": "לוויה" },
  { "id": 20, "name": "Pahaliah", "hebrew": "פהליה" },
  { "id": 21, "name": "Nelchael", "hebrew": "נלכאל" },
  { "id": 22, "name": "Ieiaiel", "hebrew": "יייאל", "attribute": "Protection (Sanctuary and shielding)" },
  { "id": 23, "name": "Melahel", "hebrew": "מלהאל" },
  { "id": 24, "name": "Hahuiah", "hebrew": "חהויה" },
  { "id": 25, "name": "Nith-Haiah", "hebrew": "נתהיה" },
  { "id": 26, "name": "Haaiah", "hebrew": "האאיה" },
  { "id": 27, "name": "Ierathel", "hebrew": "ירתאל", "attribute": "Protection (Deliverance from enemies)" },
  { "id": 28, "name": "Seheiah", "hebrew": "שאהיה" },
  { "id": 29, "name": "Reiiel", "hebrew": "רייאל" },
  { "id": 30, "name": "Omael", "hebrew": "אומאל" },
  { "id": 31, "name": "Lecabel", "hebrew": "לכבאל" },
  { "id": 32, "name": "Vasiariah", "hebrew": "ושריה" },
  { "id": 33, "name": "Iehuiah", "hebrew": "יחויה" },
  { "id": 34, "name": "Lehahiah", "hebrew": "להחיה" },
  { "id": 35, "name": "Chavakiah", "hebrew": "כוקיה" },
  { "id": 36, "name": "Menadel", "hebrew": "מנדאל" },
  { "id": 37, "name": "Aniel", "hebrew": "אניאל" },
  { "id": 38, "name": "Haamiah", "hebrew": "חעמיה" },
  { "id": 39, "name": "Rehael", "hebrew": "רהעאל" },
  { "id": 40, "name": "Ieizel", "hebrew": "ייזאל" },
  { "id": 41, "name": "Hahahel", "hebrew": "הההאל" },
  { "id": 42, "name": "Mikael", "hebrew": "מיכאל", "attribute": "Protection (Universal protection and warding)" },
  { "id": 43, "name": "Veuliah", "hebrew": "ווליה" },
  { "id": 44, "name": "Ielahiah", "hebrew": "ילהיה" },
  { "id": 45, "name": "Sealiah", "hebrew": "סאליה" },
  { "id": 46, "name": "Ariel", "hebrew": "עריאל" },
  { "id": 47, "name": "Asaliah", "hebrew": "עשליה" },
  { "id": 48, "name": "Mihael", "hebrew": "מיהאל" },
  { "id": 49, "name": "Vehuel", "hebrew": "והואל" },
  { "id": 50, "name": "Daniel", "hebrew": "דניאל" },
  { "id": 51, "name": "Hahasiah", "hebrew": "החשיה" },
  { "id": 52, "name": "Imamiah", "hebrew": "עממיה" },
  { "id": 53, "name": "Nanael", "hebrew": "ננאאל" },
  { "id": 54, "name": "Nithanael", "hebrew": "ניתאל" },
  { "id": 55, "name": "Mebahiah", "hebrew": "מבהיה" },
  { "id": 56, "name": "Poiel", "hebrew": "פויאל" },
  { "id": 57, "name": "Nemamiah", "hebrew": "נממיה", "attribute": "Protection (Spiritual resilience and shielding)" },
  { "id": 58, "name": "Ieialel", "hebrew": "יילאל" },
  { "id": 59, "name": "Harahel", "hebrew": "הרחאל" },
  { "id": 60, "name": "Mitzrael", "hebrew": "מצראל" },
  { "id": 61, "name": "Umabel", "hebrew": "ומבאל" },
  { "id": 62, "name": "Iah-hel", "hebrew": "יההאל" },
  { "id": 63, "name": "Anauel", "hebrew": "ענואל" },
  { "id": 64, "name": "Mehiel", "hebrew": "מחיאל" },
  { "id": 65, "name": "Damabiah", "hebrew": "דמביה" },
  { "id": 66, "name": "Manakel", "hebrew": "מנקאל" },
  { "id": 67, "name": "Eiael", "hebrew": "איעאל" },
  { "id": 68, "name": "Habuhiah", "hebrew": "חבויה" },
  { "id": 69, "name": "Rochel", "hebrew": "ראהאל" },
  { "id": 70, "name": "Jabamiah", "hebrew": "יבמיה" },
  { "id": 71, "name": "Haiaiel", "hebrew": "הייאל" },
  { "id": 72, "name": "Mumiah", "hebrew": "מומיה" }
]
